sphinxcontrib/t3fieldlisttable.py
sphinxcontrib/__init__.py
t3fieldlisttable-0.2.0.dist-info/DESCRIPTION.rst
t3fieldlisttable-0.2.0.dist-info/WHEEL
t3fieldlisttable-0.2.0.dist-info/metadata.json
t3fieldlisttable-0.2.0.dist-info/METADATA
t3fieldlisttable-0.2.0.dist-info/top_level.txt
t3fieldlisttable-0.2.0.dist-info/RECORD
