Metadata-Version: 2.0
Name: t3fieldlisttable
Version: 0.2.0
Summary: Implement t3-field-list-table Directive for Sphinx
Home-page: https://github.com/TYPO3-Documentation/sphinxcontrib.t3fieldlisttable
Author: Martin Bless
Author-email: martin@mbless.de
License: BSD
Keywords: sphinx extension directive
Platform: UNKNOWN
Classifier: Development Status :: 5 - Production/Stable
Classifier: Intended Audience :: End Users/Desktop
Classifier: Framework :: Sphinx :: ExtensionLicense :: OSI Approved :: BSD License
Classifier: Programming Language :: Python :: 2
Classifier: Programming Language :: Python :: 3
Classifier: Operating System :: OS Independent
Classifier: Topic :: Documentation
Requires-Dist: sphinx
